libhsmd.py
_libhsmd.cpython-37m-x86_64-linux-gnu.so
libhsmd-0.10.0.post3.dist-info/METADATA
libhsmd-0.10.0.post3.dist-info/top_level.txt
libhsmd-0.10.0.post3.dist-info/RECORD
libhsmd-0.10.0.post3.dist-info/WHEEL
